gitmoji/__init__.py
gitmoji/constants.py
gitmoji/py.typed
gitmoji-0.1.0.dist-info/LICENSE
gitmoji-0.1.0.dist-info/WHEEL
gitmoji-0.1.0.dist-info/METADATA
gitmoji-0.1.0.dist-info/RECORD
